PhyNetPy/__init__.py
PhyNetPy/ABC/__init__.py
PhyNetPy/ABC/abc_demo.py
PhyNetPy/ABC/abc_tree.py
PhyNetPy/ABC/ete3test.py
PhyNetPy/ABC/growtree.py
PhyNetPy/ABC/model.py
PhyNetPy/ABC/pps.py
PhyNetPy/ABC/rate_v_stat.py
PhyNetPy/ABC/sim_one_tree.py
PhyNetPy/Bayesian/Alphabet.py
PhyNetPy/Bayesian/BirthDeath.py
PhyNetPy/Bayesian/GTR.py
PhyNetPy/Bayesian/Graph.py
PhyNetPy/Bayesian/MSA.py
PhyNetPy/Bayesian/Matrix.py
PhyNetPy/Bayesian/MetropolisHastings.py
PhyNetPy/Bayesian/ModelGraph.py
PhyNetPy/Bayesian/Move.py
PhyNetPy/Bayesian/NetworkBuilder.py
PhyNetPy/Bayesian/Node.py
PhyNetPy/Bayesian/SNPModule.py
PhyNetPy/Bayesian/SNPTransition.py
PhyNetPy/Bayesian/SequenceSim.py
PhyNetPy/Bayesian/State.py
PhyNetPy/Bayesian/Tools.py
PhyNetPy/Bayesian/__init__.py
PhyNetPy-0.0.1.dist-info/LICENSE
PhyNetPy-0.0.1.dist-info/METADATA
PhyNetPy-0.0.1.dist-info/WHEEL
PhyNetPy-0.0.1.dist-info/top_level.txt
PhyNetPy-0.0.1.dist-info/zip-safe
PhyNetPy-0.0.1.dist-info/RECORD
