Metadata-Version: 2.1
Name: PhyNetPy
Version: 0.0.1
Summary: PhyNetPy is a library to provide not only methods, but a framework for the analysis, inference, simulation, and visualization of phylogenetic networks and trees
Home-page: https://github.com/NakhlehLab/PhyNetPy
Author: Luay Nakhleh
Author-email: nakhleh@rice.edu
Project-URL: Bug Tracker, https://github.com/NakhlehLab/PhyNetPy/issues
Classifier: Programming Language :: Python :: 3
Classifier: License :: OSI Approved :: MIT License
Classifier: Operating System :: OS Independent
Requires-Python: >=3.8
License-File: LICENSE
Requires-Dist: numpy (>=1.23.5)
Requires-Dist: biopython (>=1.8)
Requires-Dist: elfi (>=0.8.4)
Requires-Dist: ete3 (>=3.1.2)
Requires-Dist: matplotlib
Requires-Dist: newick
Requires-Dist: python-nexus (>=2.9.0)
Requires-Dist: scipy (>=1.9.3)
Provides-Extra: test
Requires-Dist: pytest ; extra == 'test'
Requires-Dist: pytest-cov ; extra == 'test'
